README.md
setup.cfg
setup.py
xboxcontroller/__init__.py
xboxcontroller/error.py
xboxcontroller/tests.py
xboxcontroller/xboxcontroller.py
xboxcontroller.egg-info/PKG-INFO
xboxcontroller.egg-info/SOURCES.txt
xboxcontroller.egg-info/dependency_links.txt
xboxcontroller.egg-info/not-zip-safe
xboxcontroller.egg-info/top_level.txt