Metadata-Version: 1.0
Name: xboxcontroller
Version: 0.1.1
Summary: Python library for using Xbox 360 controllers in linux-based systems.
Home-page: http://github.com/ricgby/xboxcontroller
Author: Ricgby
Author-email: ricardobustosglz@gmail.com
License: MIT
Platform: UNKNOWN
